{
  "Z": 0.9860144853591919,
  "best_Z_so_far": 0.9860144853591919,
  "best_iter_so_far": 0,
  "bspline_enabled": 0,
  "bspline_grad_norm": 0.0,
  "bspline_max_disp": 0.0,
  "bspline_mean_disp": 0.0,
  "bspline_num_at_max": 0,
  "bspline_num_at_min": 0,
  "bspline_p95_disp": 0.0,
  "bspline_param_max": 0.0,
  "bspline_param_mean_abs": 0.0,
  "bspline_param_min": 0.0,
  "case_id": "face_002__add_headphones",
  "clean_edit_embedding_norm": 1.0,
  "combined_max_disp_px": 1.6798701286315918,
  "combined_mean_disp_px": 0.6725682020187378,
  "combined_p95_disp_px": 1.3783050775527954,
  "components_at_boundary": "",
  "dct_clipped_high_fraction": 0.0,
  "dct_clipped_low_fraction": 0.0,
  "dct_coefficient_delta_l1": 0.0,
  "dct_coefficient_delta_l2": 0.0,
  "dct_dc_energy": 0.0,
  "dct_enabled": 0,
  "dct_frequency_mask_mode": "all_ac",
  "dct_gain_grad_norm": 0.0,
  "dct_gain_l2": 0.0,
  "dct_gain_max": 0.0,
  "dct_gain_mean": 0.0,
  "dct_gain_mean_abs": 0.0,
  "dct_gain_min": 0.0,
  "dct_high_frequency_energy_after": 0.0,
  "dct_high_frequency_energy_before": 0.0,
  "dct_input_coefficient_energy": 0.0,
  "dct_low_frequency_energy_after": 0.0,
  "dct_low_frequency_energy_before": 0.0,
  "dct_mid_frequency_energy_after": 0.0,
  "dct_mid_frequency_energy_before": 0.0,
  "dct_num_at_max": 0,
  "dct_num_at_min": 0,
  "dct_num_clamped": 0,
  "dct_output_coefficient_energy": 0.0,
  "dct_relative_energy_change": 0.0,
  "dct_selected_frequency_count": 0,
  "dct_spatial_delta_l1": 0.0,
  "dct_spatial_delta_l2": 0.0,
  "dct_spatial_delta_max_abs": 0.0,
  "dct_spatial_delta_mse": 0.0,
  "delaunay_enabled": 1,
  "delaunay_grad_norm": 0.0,
  "delaunay_max_disp": 0.45285847783088684,
  "delaunay_mean_disp": 0.141797736287117,
  "delaunay_num_at_max": 0,
  "delaunay_num_at_min": 0,
  "delaunay_p95_disp": 0.3297082483768463,
  "delaunay_param_max": 0.6219128370285034,
  "delaunay_param_mean_abs": 0.22714069485664368,
  "delaunay_param_min": -0.6244150400161743,
  "differential_surface_enabled": 1,
  "differential_surface_grad_norm": 0.0,
  "differential_surface_max_disp": 1.461806297302246,
  "differential_surface_mean_disp": 0.4204406142234802,
  "differential_surface_num_at_max": 0,
  "differential_surface_num_at_min": 0,
  "differential_surface_p95_disp": 1.0162990093231201,
  "differential_surface_param_max": 0.007946407422423363,
  "differential_surface_param_mean_abs": 0.0019117824267596006,
  "differential_surface_param_min": -0.008081093430519104,
  "edit_identity_angle_degrees": 9.593660354614258,
  "edit_identity_angle_radians": 0.16744095087051392,
  "edit_identity_cosine_distance": 0.013985514640808105,
  "edit_identity_cosine_similarity_raw": 0.9860144853591919,
  "edit_identity_l2_embedding_distance": 0.16724584996700287,
  "edit_identity_similarity_score_pct": 98.60144805908203,
  "editor_num_inference_steps": 20,
  "face_id": "face_002",
  "fft_phase_enabled": 0,
  "fft_phase_grad_norm": 0.0,
  "fft_phase_max_abs": 0.0,
  "fft_phase_mean_abs": 0.0,
  "fft_phase_norm": 0.0,
  "fft_phase_num_at_max": 0,
  "fft_phase_num_at_min": 0,
  "fft_phase_num_clamped": 0,
  "fft_spatial_delta_mse": 0.0,
  "foldover_fraction": 0.0,
  "fraction_clamped_total": 0.0,
  "geodesic_enabled": 0,
  "geodesic_grad_norm": 0.0,
  "geodesic_max_disp": 0.0,
  "geodesic_mean_disp": 0.0,
  "geodesic_num_at_max": 0,
  "geodesic_num_at_min": 0,
  "geodesic_p95_disp": 0.0,
  "geodesic_param_max": 0.0,
  "geodesic_param_mean_abs": 0.0,
  "geodesic_param_min": 0.0,
  "identity_angle_degrees": 9.593660354614258,
  "identity_angle_radians": 0.16744095087051392,
  "identity_cosine_distance": 0.013985514640808105,
  "identity_cosine_similarity_raw": 0.9860144853591919,
  "identity_l2_embedding_distance": 0.16724584996700287,
  "identity_similarity_score_pct": 98.60144805908203,
  "input_identity_angle_degrees": 7.7070112228393555,
  "input_identity_angle_radians": 0.13451272249221802,
  "input_identity_cosine_distance": 0.009033203125,
  "input_identity_cosine_similarity_raw": 0.990966796875,
  "input_identity_l2_embedding_distance": 0.13441145420074463,
  "input_identity_left_embedding_norm": 0.9999999403953552,
  "input_identity_right_embedding_norm": 1.0,
  "input_identity_similarity_score_pct": 99.0966796875,
  "iter": 0,
  "jacobian_det_min": 0.8627738952636719,
  "l2_to_original": 0.022186672315001488,
  "laplacian_enabled": 1,
  "laplacian_grad_norm": 0.0,
  "laplacian_max_disp": 0.106062151491642,
  "laplacian_mean_disp": 0.03754913806915283,
  "laplacian_num_at_max": 0,
  "laplacian_num_at_min": 0,
  "laplacian_p95_disp": 0.0838337168097496,
  "laplacian_param_max": 0.929490327835083,
  "laplacian_param_mean_abs": 0.12818072736263275,
  "laplacian_param_min": -0.609532356262207,
  "learning_rate": 0.1,
  "legacy_fft_strength_equivalent": 0.0,
  "lens_barrel_enabled": 1,
  "lens_barrel_grad_norm": 0.0,
  "lens_barrel_max_disp": 0.0806562677025795,
  "lens_barrel_mean_disp": 0.06314894556999207,
  "lens_barrel_num_at_max": 0,
  "lens_barrel_num_at_min": 0,
  "lens_barrel_p95_disp": 0.0805710107088089,
  "lens_barrel_param_max": 0.00029010657453909516,
  "lens_barrel_param_mean_abs": 0.00029010657453909516,
  "lens_barrel_param_min": 0.00029010657453909516,
  "lens_pincushion_enabled": 1,
  "lens_pincushion_grad_norm": 0.0,
  "lens_pincushion_max_disp": 0.06336140632629395,
  "lens_pincushion_mean_disp": 0.04960848391056061,
  "lens_pincushion_num_at_max": 0,
  "lens_pincushion_num_at_min": 0,
  "lens_pincushion_p95_disp": 0.06328941136598587,
  "lens_pincushion_param_max": -0.00022778805578127503,
  "lens_pincushion_param_mean_abs": 0.00022778805578127503,
  "lens_pincushion_param_min": -0.00022778805578127503,
  "loss": 0.9860144853591919,
  "mobius_enabled": 0,
  "mobius_grad_norm": 0.0,
  "mobius_max_disp": 0.0,
  "mobius_mean_disp": 0.0,
  "mobius_num_at_max": 0,
  "mobius_num_at_min": 0,
  "mobius_p95_disp": 0.0,
  "mobius_param_max": 0.0,
  "mobius_param_mean_abs": 0.0,
  "mobius_param_min": 0.0,
  "mse_to_original": 0.0004922483931295574,
  "num_at_max_total": 0,
  "num_at_min_total": 0,
  "num_clamped_total": 0,
  "num_total_params": 355,
  "original_embedding_norm": 1.0,
  "peak_vram_gb": 5.382288455963135,
  "perturbed_edit_embedding_norm": 1.0,
  "perturbed_embedding_norm": 1.0,
  "polar_enabled": 1,
  "polar_grad_norm": 0.0,
  "polar_max_disp": 1.721903681755066,
  "polar_mean_disp": 0.39900723099708557,
  "polar_p95_disp": 1.0845743417739868,
  "polar_radial_num_at_max": 0,
  "polar_radial_num_at_min": 0,
  "polar_radial_param_max": 0.13519670069217682,
  "polar_radial_param_mean_abs": 0.13519670069217682,
  "polar_radial_param_min": 0.13519670069217682,
  "polar_twist_num_at_max": 0,
  "polar_twist_num_at_min": 0,
  "polar_twist_param_max": 0.0028629235457628965,
  "polar_twist_param_mean_abs": 0.0028629235457628965,
  "polar_twist_param_min": 0.0028629235457628965,
  "prompt": "add headphones",
  "psnr_to_original": 33.078156928761935,
  "rolling_enabled": 1,
  "rolling_grad_norm": 0.0,
  "rolling_max_disp": 0.13095085322856903,
  "rolling_mean_disp": 0.046925075352191925,
  "rolling_num_at_max": 0,
  "rolling_num_at_min": 0,
  "rolling_p95_disp": 0.12146562337875366,
  "rolling_param_max": 0.14628373086452484,
  "rolling_param_mean_abs": 0.08893033862113953,
  "rolling_param_min": -0.03157694265246391,
  "seconds_elapsed": 0.0,
  "seconds_iter": 0.0,
  "seed": 438717,
  "smoothness_tv": 0.01851193606853485,
  "ssim_to_original": 0.9962449669837952,
  "total_geometry_grad_norm": 0.0,
  "total_grad_norm": 0.0,
  "tps_enabled": 1,
  "tps_grad_norm": 0.0,
  "tps_max_disp": 0.3719029128551483,
  "tps_mean_disp": 0.1072840690612793,
  "tps_num_at_max": 0,
  "tps_num_at_min": 0,
  "tps_p95_disp": 0.2692957818508148,
  "tps_param_max": 0.4875905215740204,
  "tps_param_mean_abs": 0.12964200973510742,
  "tps_param_min": -0.41967496275901794
}
